[{"__symbolic":"module","version":4,"metadata":{"Popover":{"__symbolic":"class","decorators":[{"__symbolic":"call","expression":{"__symbolic":"reference","module":"@angular/core","name":"Directive","line":3,"character":1},"arguments":[{"selector":"[popover]","exportAs":"popover"}]}],"members":{"__ctor__":[{"__symbolic":"constructor","parameters":[{"__symbolic":"reference","module":"@angular/core","name":"ViewContainerRef","line":21,"character":44},{"__symbolic":"reference","module":"@angular/core","name":"ComponentFactoryResolver","line":22,"character":36},{"__symbolic":"reference","module":"@angular/core","name":"ApplicationRef","line":23,"character":42},{"__symbolic":"reference","module":"@angular/core","name":"Injector","line":24,"character":36}]}],"content":[{"__symbolic":"property","decorators":[{"__symbolic":"call","expression":{"__symbolic":"reference","module":"@angular/core","name":"Input","line":31,"character":5},"arguments":["popover"]}]}],"popoverInBody":[{"__symbolic":"property","decorators":[{"__symbolic":"call","expression":{"__symbolic":"reference","module":"@angular/core","name":"Input","line":34,"character":5}}]}],"popoverDisabled":[{"__symbolic":"property","decorators":[{"__symbolic":"call","expression":{"__symbolic":"reference","module":"@angular/core","name":"Input","line":37,"character":5}}]}],"popoverAnimation":[{"__symbolic":"property","decorators":[{"__symbolic":"call","expression":{"__symbolic":"reference","module":"@angular/core","name":"Input","line":40,"character":5}}]}],"popoverPlacement":[{"__symbolic":"property","decorators":[{"__symbolic":"call","expression":{"__symbolic":"reference","module":"@angular/core","name":"Input","line":43,"character":5}}]}],"popoverTitle":[{"__symbolic":"property","decorators":[{"__symbolic":"call","expression":{"__symbolic":"reference","module":"@angular/core","name":"Input","line":46,"character":5}}]}],"popoverOnHover":[{"__symbolic":"property","decorators":[{"__symbolic":"call","expression":{"__symbolic":"reference","module":"@angular/core","name":"Input","line":49,"character":5}}]}],"popoverCloseOnClickOutside":[{"__symbolic":"property","decorators":[{"__symbolic":"call","expression":{"__symbolic":"reference","module":"@angular/core","name":"Input","line":52,"character":5}}]}],"popoverCloseOnMouseOutside":[{"__symbolic":"property","decorators":[{"__symbolic":"call","expression":{"__symbolic":"reference","module":"@angular/core","name":"Input","line":55,"character":5}}]}],"popoverDismissTimeout":[{"__symbolic":"property","decorators":[{"__symbolic":"call","expression":{"__symbolic":"reference","module":"@angular/core","name":"Input","line":58,"character":5}}]}],"onShown":[{"__symbolic":"property","decorators":[{"__symbolic":"call","expression":{"__symbolic":"reference","module":"@angular/core","name":"Output","line":61,"character":5}}]}],"onHidden":[{"__symbolic":"property","decorators":[{"__symbolic":"call","expression":{"__symbolic":"reference","module":"@angular/core","name":"Output","line":64,"character":5}}]}],"showOrHideOnClick":[{"__symbolic":"method","decorators":[{"__symbolic":"call","expression":{"__symbolic":"reference","module":"@angular/core","name":"HostListener","line":71,"character":5},"arguments":["click"]}]}],"showOnHover":[{"__symbolic":"method","decorators":[{"__symbolic":"call","expression":{"__symbolic":"reference","module":"@angular/core","name":"HostListener","line":78,"character":5},"arguments":["focusin"]},{"__symbolic":"call","expression":{"__symbolic":"reference","module":"@angular/core","name":"HostListener","line":79,"character":5},"arguments":["mouseenter"]}]}],"hideOnHover":[{"__symbolic":"method","decorators":[{"__symbolic":"call","expression":{"__symbolic":"reference","module":"@angular/core","name":"HostListener","line":86,"character":5},"arguments":["focusout"]},{"__symbolic":"call","expression":{"__symbolic":"reference","module":"@angular/core","name":"HostListener","line":87,"character":5},"arguments":["mouseleave"]}]}],"ngOnChanges":[{"__symbolic":"method"}],"toggle":[{"__symbolic":"method"}],"show":[{"__symbolic":"method"}],"hide":[{"__symbolic":"method"}],"getElement":[{"__symbolic":"method"}]}}}}]